django_postgresql_reconnect/__init__.py
django_postgresql_reconnect/backend/__init__.py
django_postgresql_reconnect/backend/base.py
django_postgresql_reconnect/decorator.py
django_postgresql_reconnect/helpers.py
django_postgresql_reconnect/middleware.py
django_postgresql_reconnect-1.0.4.dist-info/METADATA
django_postgresql_reconnect-1.0.4.dist-info/WHEEL
django_postgresql_reconnect-1.0.4.dist-info/RECORD
