Metadata-Version: 2.1
Name: django-postgresql-reconnect
Version: 1.0.4
Summary: 
Home-page: https://github.com/cloudblue/django-postgresql-reconnect
Author: CloudBlue LLC
Requires-Python: >=3.8,<4.0
Classifier: Development Status :: 5 - Production/Stable
Classifier: Intended Audience :: Developers
Classifier: License :: OSI Approved :: Apache Software License
Classifier: Operating System :: Unix
Classifier: Programming Language :: Python :: 3
Classifier: Programming Language :: Python :: 3.8
Classifier: Programming Language :: Python :: 3.9
Classifier: Programming Language :: Python :: 3.10
Classifier: Programming Language :: Python :: 3.11
Classifier: Topic :: Database
Requires-Dist: Django (>=3.2,<5)
Project-URL: Repository, https://github.com/cloudblue/django-postgresql-reconnect
